feishubot.py
feishubot2-0.0.3.dist-info/LICENSE
feishubot2-0.0.3.dist-info/METADATA
feishubot2-0.0.3.dist-info/WHEEL
feishubot2-0.0.3.dist-info/top_level.txt
feishubot2-0.0.3.dist-info/RECORD
