Metadata-Version: 2.1
Name: feishubot2
Version: 0.0.3
Summary: Send message to you by feishu bot.
Author-email: Dragon-GCS <878173121@qq.com>
Project-URL: Homepage, https://github.com/Dragon-GCS/feishubot
Project-URL: Bug Tracker, https://github.com/Dragon-GCS/feishubot/issues
Classifier: License :: OSI Approved :: MIT License
Classifier: Operating System :: OS Independent
Classifier: Programming Language :: Python :: 3
Classifier: Topic :: Communications
Requires-Python: >=3.6
License-File: LICENSE
Requires-Dist: loguru
Requires-Dist: requests
Requires-Dist: requests-toolbelt
Provides-Extra: dev
Provides-Extra: media
Requires-Dist: opencv-python ; extra == 'media'
